agex/__init__.py
agex/py.typed
agex/agent/__init__.py
agex/agent/base.py
agex/agent/console.py
agex/agent/datatypes.py
agex/agent/events.py
agex/agent/fingerprint.py
agex/agent/formatting.py
agex/agent/primer_text.py
agex/agent/registration.py
agex/agent/summarization.py
agex/agent/task.py
agex/agent/task.pyi
agex/agent/task_messages.py
agex/agent/utils.py
agex/agent/loop/__init__.py
agex/agent/loop/async_loop.py
agex/agent/loop/common.py
agex/agent/loop/mixin.py
agex/agent/loop/sync_loop.py
agex/agent/policy/__init__.py
agex/agent/policy/datatypes.py
agex/agent/policy/describe.py
agex/agent/policy/policy.py
agex/agent/policy/resolve.py
agex/bench/__init__.py
agex/bench/aggregators.py
agex/bench/core.py
agex/bench/types.py
agex/eval/analysis.py
agex/eval/arguments.py
agex/eval/base.py
agex/eval/binop.py
agex/eval/builtins.py
agex/eval/call.py
agex/eval/comprehension.py
agex/eval/constants.py
agex/eval/core.py
agex/eval/error.py
agex/eval/expressions.py
agex/eval/functions.py
agex/eval/loops.py
agex/eval/objects.py
agex/eval/resolver.py
agex/eval/statements.py
agex/eval/user_errors.py
agex/eval/utils.py
agex/eval/validation.py
agex/helpers/__init__.py
agex/helpers/numpy_helper.py
agex/helpers/pandas_helper.py
agex/helpers/plotly_helper.py
agex/helpers/stdlib.py
agex/llm/__init__.py
agex/llm/anthropic_client.py
agex/llm/config.py
agex/llm/core.py
agex/llm/dummy_client.py
agex/llm/gemini_client.py
agex/llm/openai_client.py
agex/llm/xml.py
agex/render/capabilities.py
agex/render/context.py
agex/render/definitions.py
agex/render/events.py
agex/render/primitives.py
agex/render/stream.py
agex/render/token_count.py
agex/render/value.py
agex/render/view.py
agex/render/xml.py
agex/state/__init__.py
agex/state/closure.py
agex/state/core.py
agex/state/gc.py
agex/state/kv.py
agex/state/live.py
agex/state/log.py
agex/state/namespaced.py
agex/state/scoped.py
agex/state/versioned.py
agex/tokenizers/__init__.py
agex/tokenizers/core.py
agex/tokenizers/tiktoken.py
agex-0.7.1.dist-info/licenses/LICENSE
agex-0.7.1.dist-info/METADATA
agex-0.7.1.dist-info/WHEEL
agex-0.7.1.dist-info/top_level.txt
agex-0.7.1.dist-info/RECORD
