Metadata-Version: 2.4
Name: agex
Version: 0.7.1
Summary: Library-friendly agents that work directly with your existing Python codebase.
Author: ashenfad
License-Expression: MIT
Project-URL: Homepage, https://ashenfad.github.io/agex/
Project-URL: Documentation, https://ashenfad.github.io/agex/
Project-URL: Repository, https://github.com/ashenfad/agex
Project-URL: Issues, https://github.com/ashenfad/agex/issues
Keywords: agents,ai,llm,python,runtime,sandbox
Classifier: Development Status :: 4 - Beta
Classifier: Intended Audience :: Developers
Classifier: Programming Language :: Python :: 3
Classifier: Programming Language :: Python :: 3.10
Classifier: Programming Language :: Python :: 3.11
Classifier: Programming Language :: Python :: 3.12
Classifier: Programming Language :: Python :: 3.13
Classifier: Programming Language :: Python :: 3.14
Classifier: Topic :: Scientific/Engineering :: Artificial Intelligence
Classifier: Topic :: Software Development :: Libraries :: Python Modules
Requires-Python: >=3.10
License-File: LICENSE
Requires-Dist: tiktoken
Requires-Dist: xxhash
Requires-Dist: diskcache
Requires-Dist: pydantic
Requires-Dist: pygments
Provides-Extra: dev
Requires-Dist: ruff; extra == "dev"
Requires-Dist: pre-commit; extra == "dev"
Requires-Dist: pytest; extra == "dev"
Provides-Extra: test
Requires-Dist: pytest; extra == "test"
Requires-Dist: pytest-asyncio; extra == "test"
Requires-Dist: anyio; extra == "test"
Requires-Dist: numpy; extra == "test"
Requires-Dist: pandas; extra == "test"
Requires-Dist: anthropic; extra == "test"
Requires-Dist: google-genai; extra == "test"
Requires-Dist: openai; extra == "test"
Requires-Dist: matplotlib; extra == "test"
Provides-Extra: examples
Requires-Dist: plotly[express]; extra == "examples"
Requires-Dist: kaleido; extra == "examples"
Requires-Dist: numpy; extra == "examples"
Requires-Dist: nbformat; extra == "examples"
Requires-Dist: pandas; extra == "examples"
Requires-Dist: osmnx>=2.0.0; extra == "examples"
Requires-Dist: folium; extra == "examples"
Provides-Extra: openai
Requires-Dist: openai; extra == "openai"
Provides-Extra: anthropic
Requires-Dist: anthropic; extra == "anthropic"
Provides-Extra: gemini
Requires-Dist: google-genai; extra == "gemini"
Provides-Extra: all-providers
Requires-Dist: agex[openai]; extra == "all-providers"
Requires-Dist: agex[anthropic]; extra == "all-providers"
Requires-Dist: agex[gemini]; extra == "all-providers"
Dynamic: license-file
